[
  {
    "title": "How to Find an Apartment Without Getting Overwhelmed",
    "difficulty": "beginner",
    "tags": ["apartment-search", "planning", "first-time-renters"],
    "series": {
      "name": "Apartment Search Essentials",
      "part": 1,
      "total": 4,
      "next": "how-to-build-a-realistic-apartment-search-budget"
    }
  },
  {
    "title": "How to Build a Realistic Apartment Search Budget",
    "difficulty": "beginner",
    "tags": ["budgeting", "rent-costs", "planning"],
    "series": {
      "name": "Apartment Search Essentials",
      "part": 2,
      "total": 4,
      "previous": "how-to-find-an-apartment-without-getting-overwhelmed",
      "next": "how-to-compare-apartments-beyond-the-rent-price"
    }
  },
  {
    "title": "How to Compare Apartments Beyond the Rent Price",
    "difficulty": "beginner",
    "tags": ["comparison", "rent-costs", "decision-making"],
    "series": {
      "name": "Apartment Search Essentials",
      "part": 3,
      "total": 4,
      "previous": "how-to-build-a-realistic-apartment-search-budget",
      "next": "how-to-choose-between-two-good-apartments"
    }
  },
  {
    "title": "How to Choose Between Two Good Apartments",
    "difficulty": "intermediate",
    "tags": ["decision-making", "tradeoffs", "apartment-search"],
    "series": {
      "name": "Apartment Search Essentials",
      "part": 4,
      "total": 4,
      "previous": "how-to-compare-apartments-beyond-the-rent-price"
    }
  },
  {
    "title": "Red Flags to Watch for in Apartment Listings",
    "difficulty": "beginner",
    "tags": ["red-flags", "listings", "renter-safety"],
    "series": {
      "name": "Spotting Rental Red Flags",
      "part": 1,
      "total": 4,
      "next": "how-to-spot-rental-scams-before-you-apply"
    }
  },
  {
    "title": "How to Spot Rental Scams Before You Apply",
    "difficulty": "beginner",
    "tags": ["scams", "renter-safety", "applications"],
    "series": {
      "name": "Spotting Rental Red Flags",
      "part": 2,
      "total": 4,
      "previous": "red-flags-to-watch-for-in-apartment-listings",
      "next": "negative-signs-of-a-poorly-managed-rental"
    }
  },
  {
    "title": "Negative Signs of a Poorly Managed Rental",
    "difficulty": "intermediate",
    "tags": ["red-flags", "property-management", "renter-safety"],
    "series": {
      "name": "Spotting Rental Red Flags",
      "part": 3,
      "total": 4,
      "previous": "how-to-spot-rental-scams-before-you-apply",
      "next": "what-to-do-when-an-apartment-tour-feels-off"
    }
  },
  {
    "title": "What to Do When an Apartment Tour Feels Off",
    "difficulty": "intermediate",
    "tags": ["tours", "red-flags", "decision-making"],
    "series": {
      "name": "Spotting Rental Red Flags",
      "part": 4,
      "total": 4,
      "previous": "negative-signs-of-a-poorly-managed-rental"
    }
  },
  {
    "title": "Questions to Ask Before Touring an Apartment",
    "difficulty": "beginner",
    "tags": ["tours", "questions", "apartment-search"]
  },
  {
    "title": "What to Check During an Apartment Walkthrough",
    "difficulty": "beginner",
    "tags": ["walkthrough", "inspection", "move-in"]
  },
  {
    "title": "Positive Signs of a Well-Managed Apartment Building",
    "difficulty": "beginner",
    "tags": ["positive-signs", "property-management", "quality"]
  },
  {
    "title": "Apartment Amenities That Actually Matter",
    "difficulty": "beginner",
    "tags": ["amenities", "tradeoffs", "decision-making"]
  },
  {
    "title": "Rent Specials: When They Help and When They Hide Costs",
    "difficulty": "intermediate",
    "tags": ["rent-specials", "budgeting", "tradeoffs"]
  },
  {
    "title": "What Renters Should Know About Application Fees",
    "difficulty": "beginner",
    "tags": ["applications", "fees", "budgeting"]
  },
  {
    "title": "How to Prepare a Strong Rental Application",
    "difficulty": "beginner",
    "tags": ["applications", "documents", "planning"]
  },
  {
    "title": "How to Read a Lease Before You Sign",
    "difficulty": "intermediate",
    "tags": ["lease", "renter-rights", "legal-basics"],
    "series": {
      "name": "Lease and Move-In Basics",
      "part": 1,
      "total": 4,
      "next": "what-renters-should-know-about-security-deposits"
    }
  },
  {
    "title": "What Renters Should Know About Security Deposits",
    "difficulty": "intermediate",
    "tags": ["security-deposits", "lease", "move-in"],
    "series": {
      "name": "Lease and Move-In Basics",
      "part": 2,
      "total": 4,
      "previous": "how-to-read-a-lease-before-you-sign",
      "next": "how-to-document-apartment-condition-before-move-in"
    }
  },
  {
    "title": "How to Document Apartment Condition Before Move-In",
    "difficulty": "beginner",
    "tags": ["move-in", "documentation", "security-deposits"],
    "series": {
      "name": "Lease and Move-In Basics",
      "part": 3,
      "total": 4,
      "previous": "what-renters-should-know-about-security-deposits",
      "next": "how-to-handle-maintenance-requests-after-you-move-in"
    }
  },
  {
    "title": "How to Handle Maintenance Requests After You Move In",
    "difficulty": "intermediate",
    "tags": ["maintenance", "property-management", "renter-rights"],
    "series": {
      "name": "Lease and Move-In Basics",
      "part": 4,
      "total": 4,
      "previous": "how-to-document-apartment-condition-before-move-in"
    }
  },
  {
    "title": "How to Evaluate Neighborhood Fit Before Moving",
    "difficulty": "intermediate",
    "tags": ["neighborhoods", "commute", "lifestyle"]
  },
  {
    "title": "How to Estimate Utilities Before Renting",
    "difficulty": "beginner",
    "tags": ["utilities", "budgeting", "rent-costs"]
  },
  {
    "title": "Parking, Pets, and Fees: Hidden Costs Renters Miss",
    "difficulty": "beginner",
    "tags": ["fees", "parking", "pets"]
  },
  {
    "title": "Pros and Cons of Large Apartment Communities",
    "difficulty": "intermediate",
    "tags": ["tradeoffs", "apartment-communities", "property-management"]
  },
  {
    "title": "Pros and Cons of Renting from Small Landlords",
    "difficulty": "intermediate",
    "tags": ["tradeoffs", "small-landlords", "property-management"]
  },
  {
    "title": "How to Decide Whether to Renew Your Lease",
    "difficulty": "intermediate",
    "tags": ["lease-renewal", "decision-making", "rent-costs"]
  },
  {
    "title": "What Makes an Apartment Good for Remote Work",
    "difficulty": "beginner",
    "tags": ["remote-work", "layout", "amenities"]
  },
  {
    "title": "How to Think About Roommates Before Signing a Lease",
    "difficulty": "intermediate",
    "tags": ["roommates", "lease", "planning"]
  },
  {
    "title": "How to Compare Floor Plans Like a Renter",
    "difficulty": "beginner",
    "tags": ["floor-plans", "layout", "comparison"]
  },
  {
    "title": "When a Cheaper Apartment Costs More in the Long Run",
    "difficulty": "intermediate",
    "tags": ["budgeting", "tradeoffs", "rent-costs"]
  },
  {
    "title": "How to Research an Apartment Building Before Applying",
    "difficulty": "intermediate",
    "tags": ["research", "reviews", "renter-safety"]
  }
]
